[
  {
    "_time": 20180701,
    "cpu": 88
  },
  {
    "_time": 20180702,
    "cpu": 100
  },
  {
    "_time": 20180703,
    "cpu": 66
  },
  {
    "_time": 20180704,
    "cpu": 61
  },
  {
    "_time": 20180705,
    "cpu": 73
  },
  {
    "_time": 20180706,
    "cpu": 71
  },
  {
    "_time": 20180709,
    "cpu": 34
  },
  {
    "_time": 20180710,
    "cpu": 33
  },
  {
    "_time": 20180711,
    "cpu": 47
  },
  {
    "_time": 20180712,
    "cpu": 47
  },
  {
    "_time": 20180713,
    "cpu": 100
  },
  {
    "_time": 20180714,
    "cpu": 38
  },
  {
    "_time": 20180716,
    "cpu": 22
  },
  {
    "_time": 20180717,
    "cpu": 65
  },
  {
    "_time": 20180718,
    "cpu": 36
  },
  {
    "_time": 20180719,
    "cpu": 17
  },
  {
    "_time": 20180720,
    "cpu": 36
  },
  {
    "_time": 20180721,
    "cpu": 39
  },
  {
    "_time": 20180722,
    "cpu": 95
  },
  {
    "_time": 20180723,
    "cpu": 68
  },
  {
    "_time": 20180724,
    "cpu": 19
  },
  {
    "_time": 20180725,
    "cpu": 36
  },
  {
    "_time": 20180726,
    "cpu": 23
  },
  {
    "_time": 20180727,
    "cpu": 32
  },
  {
    "_time": 20180728,
    "cpu": 37
  },
  {
    "_time": 20180729,
    "cpu": 58
  },
  {
    "_time": 20180730,
    "cpu": 32
  },
  {
    "_time": 20180731,
    "cpu": 100
  },
  {
    "_time": 20180801,
    "cpu": 30
  },
  {
    "_time": 20180802,
    "cpu": 12
  },
  {
    "_time": 20180803,
    "cpu": 20
  },
  {
    "_time": 20180804,
    "cpu": 14
  },
  {
    "_time": 20180805,
    "cpu": 39
  },
  {
    "_time": 20180806,
    "cpu": 54
  },
  {
    "_time": 20180807,
    "cpu": 38
  },
  {
    "_time": 20180808,
    "cpu": 92
  },
  {
    "_time": 20180809,
    "cpu": 35
  },
  {
    "_time": 20180810,
    "cpu": 100
  },
  {
    "_time": 20180811,
    "cpu": 28
  },
  {
    "_time": 20180812,
    "cpu": 39
  },
  {
    "_time": 20180813,
    "cpu": 48
  },
  {
    "_time": 20180814,
    "cpu": 58
  },
  {
    "_time": 20180815,
    "cpu": 21
  },
  {
    "_time": 20180816,
    "cpu": 61
  },
  {
    "_time": 20180817,
    "cpu": 53
  },
  {
    "_time": 20180818,
    "cpu": 78
  },
  {
    "_time": 20180820,
    "cpu": 53
  }
]
